brewing/__init__.py
brewing/__main__.py
brewing/app.py
brewing/generic.py
brewing/plugin.py
brewing/py.typed
brewing/cli/__init__.py
brewing/cli/cli.py
brewing/cli/py.typed
brewing/cli/testing.py
brewing/db/__init__.py
brewing/db/base.py
brewing/db/columns.py
brewing/db/database.py
brewing/db/migrate.py
brewing/db/mixins.py
brewing/db/py.typed
brewing/db/settings.py
brewing/db/testing.py
brewing/db/types.py
brewing/db/_migrationcontext/README
brewing/db/_migrationcontext/__init__.py
brewing/db/_migrationcontext/env.py
brewing/db/_migrationcontext/script.py.mako
brewing/db/compose/__init__.py
brewing/db/compose/compose.mysql.yaml
brewing/db/compose/compose.postgresql.yaml
brewing/healthcheck/__init__.py
brewing/healthcheck/viewset.py
brewing/http/__init__.py
brewing/http/annotations.py
brewing/http/asgi.py
brewing/http/endpoint_decorator.py
brewing/http/path.py
brewing/http/testing.py
brewing/http/viewset.py
brewing/project/__init__.py
brewing/project/cli.py
brewing/project/generation.py
brewing/project/pyproject.py
brewing/project/state.py
brewing-0.0.11.dist-info/METADATA
brewing-0.0.11.dist-info/WHEEL
brewing-0.0.11.dist-info/entry_points.txt
brewing-0.0.11.dist-info/RECORD
